imio.patterns-1.0a5-py3.12-nspkg.pth
imio/patterns/__init__.py
imio/patterns/configure.zcml
imio/patterns/interfaces.py
imio/patterns/permissions.zcml
imio/patterns/profiles.zcml
imio/patterns/setuphandlers.py
imio/patterns/testing.py
imio/patterns/browser/__init__.py
imio/patterns/browser/configure.zcml
imio/patterns/browser/overrides/.gitkeep
imio/patterns/browser/static/.gitkeep
imio/patterns/browser/static/css/imio-patterns-bundle-compiled.css
imio/patterns/browser/static/css/slick.css
imio/patterns/browser/static/fonts/slick.eot
imio/patterns/browser/static/fonts/slick.svg
imio/patterns/browser/static/fonts/slick.ttf
imio/patterns/browser/static/fonts/slick.woff
imio/patterns/browser/static/less/imio-patterns-bundle-compiled.less.map
imio/patterns/browser/static/less/imio-patterns-bundle.less
imio/patterns/browser/static/less/theme-compiled.less.map
imio/patterns/browser/static/pattern/i18n.js
imio/patterns/browser/static/pattern/imio-patterns-bundle-compiled.js
imio/patterns/browser/static/pattern/imio.pattern.js
imio/patterns/browser/static/pattern/pattern.slick.js
imio/patterns/browser/static/pattern/slick.js
imio/patterns/browser/static/pattern/slick.min.js
imio/patterns/locales/README.rst
imio/patterns/locales/__init__.py
imio/patterns/locales/imio.patterns.pot
imio/patterns/locales/update.py
imio/patterns/locales/update.sh
imio/patterns/locales/en/LC_MESSAGES/imio.patterns.po
imio/patterns/profiles/base/browserlayer.xml
imio/patterns/profiles/base/catalog.xml
imio/patterns/profiles/base/metadata.xml
imio/patterns/profiles/base/rolemap.xml
imio/patterns/profiles/plone5/metadata.xml
imio/patterns/profiles/plone5/registry.xml
imio/patterns/profiles/plone6/metadata.xml
imio/patterns/profiles/plone6/registry.xml
imio/patterns/profiles/uninstall/browserlayer.xml
imio/patterns/tests/__init__.py
imio/patterns/tests/test_robot.py
imio/patterns/tests/test_setup.py
imio/patterns/tests/robot/test_example.robot
imio/patterns/upgrades/configure.zcml
imio_patterns-1.0a5.dist-info/licenses/LICENSE.GPL
imio_patterns-1.0a5.dist-info/licenses/LICENSE.rst
imio_patterns-1.0a5.dist-info/METADATA
imio_patterns-1.0a5.dist-info/WHEEL
imio_patterns-1.0a5.dist-info/entry_points.txt
imio_patterns-1.0a5.dist-info/namespace_packages.txt
imio_patterns-1.0a5.dist-info/top_level.txt
imio_patterns-1.0a5.dist-info/RECORD
